setup.py
PyGGI.egg-info/PKG-INFO
PyGGI.egg-info/SOURCES.txt
PyGGI.egg-info/dependency_links.txt
PyGGI.egg-info/requires.txt
PyGGI.egg-info/top_level.txt
pyggi/__init__.py
pyggi/cairo.py
pyggi/cairo__CairoPattern.py
pyggi/gdk_types.py
pyggi/gio.py
pyggi/gio__.py
pyggi/gio__GAppInfo.py
pyggi/gio__GAppLauncContext.py
pyggi/gio__GApplication.py
pyggi/gio__GCancellable.py
pyggi/gio__GDrive.py
pyggi/gio__GFile.py
pyggi/gio__GFileAttributeInfoList.py
pyggi/gio__GFileAttributeMatcher.py
pyggi/gio__GFileEnumerator.py
pyggi/gio__GFileIOStream.py
pyggi/gio__GFileInfo.py
pyggi/gio__GFileInputStream.py
pyggi/gio__GFileMonitor.py
pyggi/gio__GFileOutputStream.py
pyggi/gio__GIOStream.py
pyggi/gio__GIcon.py
pyggi/gio__GInputStream.py
pyggi/gio__GInterface.py
pyggi/gio__GMount.py
pyggi/gio__GOutputStream.py
pyggi/gio__GVolume.py
pyggi/gio__gio__GFileOutputStream.py
pyggi/gio_enums.py
pyggi/gio_types.py
pyggi/gobject.py
pyggi/gobjectGEmblemedIcon.if.py
pyggi/gobject__GBoxed.py
pyggi/gobject__GByteArray.py
pyggi/gobject__GBytes.py
pyggi/gobject__GCancellable.py
pyggi/gobject__GEmbelemedIcon.py
pyggi/gobject__GEmblemedIcon.py
pyggi/gobject__GList.py
pyggi/gobject__GMainContext.py
pyggi/gobject__GMainLoop.py
pyggi/gobject__GObject.py
pyggi/gobject__GOptionGroup.py
pyggi/gobject__GParamSpec.py
pyggi/gobject__GPollFD.py
pyggi/gobject__GSList.py
pyggi/gobject__GSource.py
pyggi/gobject__GString.py
pyggi/gobject__GValue.py
pyggi/gobject_enums.py
pyggi/gobject_types.py
pyggi/gtk3.py
pyggi/gtk3_.py
pyggi/gtk3__.py
pyggi/gtk3__CairoPattern.py
pyggi/gtk3__GIcon.py
pyggi/gtk3__GList.py
pyggi/gtk3__GObject.py
pyggi/gtk3__GParamSpec.py
pyggi/gtk3__GSList.py
pyggi/gtk3__GdkAppLaunchContext.py
pyggi/gtk3__GdkAtom.py
pyggi/gtk3__GdkColor.py
pyggi/gtk3__GdkCursor.py
pyggi/gtk3__GdkDevice.py
pyggi/gtk3__GdkDeviceManager.py
pyggi/gtk3__GdkDisplay.py
pyggi/gtk3__GdkDragContext.py
pyggi/gtk3__GdkGeometry.py
pyggi/gtk3__GdkPixbuf.py
pyggi/gtk3__GdkPixbufAnimation.py
pyggi/gtk3__GdkPixbufAnimationIter.py
pyggi/gtk3__GdkPixbufSimpleAnim.py
pyggi/gtk3__GdkScreen.py
pyggi/gtk3__GdkVisual.py
pyggi/gtk3__GdkWindow.py
pyggi/gtk3__GdkWindowAttr.py
