Metadata-Version: 1.0
Name: PyGGI
Version: 1.1.0
Summary: A binding for webkitgtk and gtk (gdk,...)
Home-page: http://github.com/nak/pyggi
Author: John Rusnak
Author-email: john.j.rusnak@att.net
License: LGPL
Keywords: webkit python pywebkit gtk binding
Platform: UNKNOWN
